SphinxExtensions/__init__.py
SphinxExtensions-0.2.0.dist-info/LICENSE.md
SphinxExtensions-0.2.0.dist-info/METADATA
SphinxExtensions-0.2.0.dist-info/WHEEL
SphinxExtensions-0.2.0.dist-info/top_level.txt
SphinxExtensions-0.2.0.dist-info/RECORD
