Metadata-Version: 2.1
Name: SphinxExtensions
Version: 0.2.0
Summary: Extensions for the Sphinx documentation tool.
Home-page: https://github.com/Paebbels/SphinxExtensions
Author: Patrick Lehmann
Author-email: Paebbels@gmail.com
License: UNKNOWN
Project-URL: Documentation, https://SphinxExtensions.readthedocs.io/en/latest/
Project-URL: Source Code, https://github.com/Paebbels/SphinxExtensions
Project-URL: Issue Tracker, https://github.com/Paebbels/SphinxExtensions/issues
Keywords: Python3 Sphinx-Extension
Platform: UNKNOWN
Classifier: License :: OSI Approved :: Apache Software License
Classifier: Operating System :: OS Independent
Classifier: Programming Language :: Python :: 3 :: Only
Classifier: Programming Language :: Python :: 3.5
Classifier: Programming Language :: Python :: 3.6
Classifier: Programming Language :: Python :: 3.7
Classifier: Programming Language :: Python :: 3.8
Classifier: Development Status :: 4 - Beta
Classifier: Framework :: Sphinx :: Extension
Classifier: Topic :: Utilities
Requires-Python: >=3.5
